{"namedChunkGroups":{"polyfill":{"name":"polyfill","assets":[{"name":"webpack-runtime-5d380f73ca97c982240f.js"},{"name":"polyfill-8aacde6ebf08dc8d92dd.js"}],"filteredAssets":0,"assetsSize":null,"filteredAuxiliaryAssets":2,"auxiliaryAssetsSize":null},"app":{"name":"app","assets":[{"name":"webpack-runtime-5d380f73ca97c982240f.js"},{"name":"framework-8deecc992593cd40c3df.js"},{"name":"app-b1f2507cd0c02949801c.js"}],"filteredAssets":0,"assetsSize":null,"filteredAuxiliaryAssets":3,"auxiliaryAssetsSize":null},"component---src-pages-404-js":{"name":"component---src-pages-404-js","assets":[{"name":"component---src-pages-404-js-f8bfb63ec6d78ccb3b4e.js"}],"filteredAssets":0,"assetsSize":null,"filteredAuxiliaryAssets":1,"auxiliaryAssetsSize":null},"component---src-pages-index-js":{"name":"component---src-pages-index-js","assets":[{"name":"styles.5dab789622c818e63645.css"},{"name":"component---src-pages-index-js-ced0830f534eaaf8d673.js"}],"filteredAssets":0,"assetsSize":null,"filteredAuxiliaryAssets":2,"auxiliaryAssetsSize":null}},"assetsByChunkName":{"polyfill":["webpack-runtime-5d380f73ca97c982240f.js","polyfill-8aacde6ebf08dc8d92dd.js"],"app":["webpack-runtime-5d380f73ca97c982240f.js","framework-8deecc992593cd40c3df.js","app-b1f2507cd0c02949801c.js"],"component---src-pages-404-js":["component---src-pages-404-js-f8bfb63ec6d78ccb3b4e.js"],"component---src-pages-index-js":["styles.5dab789622c818e63645.css","component---src-pages-index-js-ced0830f534eaaf8d673.js"]},"childAssetsByChunkName":{}}